{
    "angle": {
        "branch": "main",
        "repo": "git@github.com:google/angle",
        "rev": "2641424960b5e80c7ca404652ba96b838c545b0d",
        "type": "git"
    },
    "chromium-aarch64-darwin": {
        "sha256": "1sjriz6rqfdq3d83l2i6c84vxy1sa4hw95pfhazd66v0n0pm9wzg",
        "type": "file",
        "url": "https://www.googleapis.com/download/storage/v1/b/chromium-browser-snapshots/o/Mac_Arm%2F1379013%2Fchrome-mac.zip?alt=media",
        "url_template": "https://www.googleapis.com/download/storage/v1/b/chromium-browser-snapshots/o/Mac_Arm%2F<version>%2Fchrome-mac.zip?alt=media",
        "version": "1379013"
    },
    "k3s-aarch64-linux": {
        "sha256": "11n5fv9146kgx2mq30g7ykw282jbzbgv7cjc8xp7rg2k0pwnmkk2",
        "type": "file",
        "url": "https://github.com/k3s-io/k3s/releases/download/v1.28.7+k3s1/k3s-arm64",
        "url_template": "https://github.com/k3s-io/k3s/releases/download/<version>/k3s-arm64",
        "version": "v1.28.7+k3s1"
    },
    "libepoxy": {
        "branch": "master",
        "repo": "git@github.com:anholt/libepoxy",
        "rev": "e98617e62e74a835d4e403cd270afaf296afe839",
        "type": "git"
    },
    "qemu": {
        "sha256": "12d8pga3gss613yhcmz4dqiryqbbldih0cgk02al9zwiakdgkh3x",
        "type": "file",
        "url": "https://download.qemu.org/qemu-9.1.1.tar.xz",
        "url_template": "https://download.qemu.org/qemu-<version>.tar.xz",
        "version": "9.1.1"
    },
    "socket_vmnet": {
        "branch": "master",
        "repo": "git@github.com:lima-vm/socket_vmnet",
        "rev": "f486d475d4842bbddfe8f66ba09f7d1cb10cfbed",
        "type": "git"
    },
    "virglrenderer": {
        "branch": "main",
        "repo": "https://gitlab.freedesktop.org/virgl/virglrenderer.git",
        "rev": "41f2587c008342767ccf9c5b1547cc0b96a882d4",
        "type": "git"
    },
    "virglrenderer-akihikodaki": {
        "branch": "macos",
        "repo": "git@github.com:akihikodaki/virglrenderer",
        "rev": "4a489584344787ea52226ac50dd9fa86a1f38f90",
        "type": "git"
    },
    "virglrenderer-utm": {
        "branch": "macos",
        "repo": "git@github.com:utmapp/virglrenderer",
        "rev": "dc039d9ecd74fc671a85bfbe7c4e4bc552b7b855",
        "type": "git"
    }
}
